[
	{
		"name": "Roger Federer",
		"age": "25",
		"height": "170",
		"weight": "65",
		"rank": "1"
	},
	{
		"name": "Novak Djokovic",
		"age": "24",
		"height": "172",
		"weight": "66",
		"rank": "2"
	},
	{
		
		"name": "Rafael Nadal",
		"age": "23",
		"height": "173",
		"weight": "67",
		"rank": "3"
	},
	{
		
		"name": "Andre Agassi",
		"age": "22",
		"height": "174",
		"weight": "66",
		"rank": "4"
	},
	{
		
		"name": "Pete Sampras",
		"age": "21",
		"height": "175",
		"weight": "67",
		"rank": "5"
	},
	{
		
		"name": "Dominic Thiem",
		"age": "25",
		"height": "170",
		"weight": "65",
		"rank": "6"
	},
	{
		
		"name": "Björn Borg",
		"age": "25",
		"height": "170",
		"weight": "65",
		"rank": "7"
	},
	{
		
		"name": "Hegazy",
		"age": "25",
		"height": "170",
		"weight": "65",
		"rank": "8"
	},
	{
		
		"name": "John McEnroe",
		"age": "25",
		"height": "170",
		"weight": "65",
		"rank": "9"
	},
	{
		
		"name": "Arthur Ashe",
		"age": "25",
		"height": "170",
		"weight": "65",
		"rank": "11"
	}
	
]